reliefcpp-0.2.dist-info/RECORD
reliefcpp-0.2.dist-info/top_level.txt
reliefcpp-0.2.dist-info/METADATA
reliefcpp-0.2.dist-info/WHEEL
reliefcpp-0.2.dist-info/LICENSE
reliefcpp/__init__.py
reliefcpp/_c_relief.cpython-310-x86_64-linux-gnu.so
reliefcpp/utils.py
reliefcpp/python_source.py
