Metadata-Version: 2.1
Name: reliefcpp
Version: 0.2
Summary: reliefcpp is a package for running the relief feature ranking algorithm.
Home-page: https://github.com/ferrocactus/reliefcpp
Author: Euxhen Hasanaj
Author-email: ehasanaj@cs.cmu.edu
License: MIT
Keywords: relief,reliefcpp
Platform: ALL
Provides: reliefcpp
Requires-Python: >=3.7
License-File: LICENSE
